AUTHORS.rst
CONTRIBUTING.rst
HISTORY.rst
LICENSE
MANIFEST.in
README.rst
setup.cfg
setup.py
freeplane_helper.egg-info/PKG-INFO
freeplane_helper.egg-info/SOURCES.txt
freeplane_helper.egg-info/dependency_links.txt
freeplane_helper.egg-info/entry_points.txt
freeplane_helper.egg-info/not-zip-safe
freeplane_helper.egg-info/requires.txt
freeplane_helper.egg-info/top_level.txt
freeplanehelper/__init__.py
freeplanehelper/__main__.py
tests/__init__.py
tests/test_freeplanehelper.py