Metadata-Version: 1.1
Name: freeplane-helper
Version: 0.0.5
Summary: A script that help convert FreePlane document to other formats
Home-page: https://github.com/starofrainnight/freeplane-helper
Author: Hong-She Liang
Author-email: starofrainnight@gmail.com
License: Apache Software License
Keywords: freeplanehelper,freeplane-helper
Platform: UNKNOWN
Classifier: Development Status :: 2 - Pre-Alpha
Classifier: Intended Audience :: Developers
Classifier: License :: OSI Approved :: Apache Software License
Classifier: Programming Language :: Python :: 3
Classifier: Programming Language :: Python :: 3.4
Classifier: Programming Language :: Python :: 3.5
Classifier: Programming Language :: Python :: 3.6
